{
  "subject": "stocky older humanoid figure with dark mustache in layered green coat, arms crossed, with ghostly face looming behind",
  "subject_known_ip": false,
  "suspected_ip": "Cid (Final Fantasy Legend)",
  "ip_confidence": "high",
  "ip_verified": false,
  "description": "A semi-realistic older humanoid figure stands with arms firmly crossed, wearing a layered green coat with prominent gold epaulettes and visible earrings. The face features a thick dark mustache and a stern, weathered expression. Behind the foreground figure, a large faded ghost-image of the same face looms — a stylistic double-exposure effect emphasizing gravitas. The background is a muted parchment tone with the ghost figure rendered in translucent pale lines. No weapon is visible; the figure's hands are folded into the crossed-arm pose.",
  "facing": "forward",
  "composition": "mid-shot",
  "mode": "portrait",
  "figure_count": "solo",
  "foreground": "older figure in green coat with gold epaulettes, arms crossed, dark mustache",
  "foreground_palette": ["green", "gold", "dark-brown", "cream"],
  "background": "parchment cream with ghostly face double-exposure",
  "background_palette": ["cream", "pale-gray", "off-white"],
  "setting": "void",
  "architecture": "none",
  "time_of_day": "indeterminate",
  "weather": "none",
  "mood": "grim",
  "genre_cues": ["fantasy", "jrpg", "anime"],
  "lighting": "soft",
  "objects": [],
  "animals_creatures": [],
  "food_drink": [],
  "clothing_style": "formal",
  "iconography": [],
  "emotion": "stern, arms crossed, weathered confidence, defiant",
  "tags_hub": ["helmsman", "sailor", "captain", "elder", "mustache", "arms-crossed", "ghost", "double-exposure", "jrpg", "final-fantasy"],
  "tags_filter": ["solo", "mid-shot", "forward-facing", "portrait-mode", "male-figure", "unarmed"],
  "vision_uncertainty": ["low-resolution-source"]
}
