{
  "subject": "Champa, Universe 6 Destroyer God, gesturing with one hand raised, seated or posed in authority",
  "subject_known_ip": false,
  "suspected_ip": "Champa (Dragon Ball Super)",
  "ip_confidence": "high",
  "ip_verified": false,
  "description": "A rotund, purple cat-eared humanoid figure is depicted in a commanding pose, one arm raised with finger pointed or gesturing upward. The figure wears a dark vest-like garment with lighter trims. Behind the figure, purple and lavender energy swirls fill the background. The composition is a mid-shot with a slightly more measured, authoritative feel compared to a purely combat-action pose. The figure's expression reads as smug or scheming. The background palette is purple with soft magenta gradients.",
  "facing": "three-quarter",
  "composition": "mid-shot",
  "mode": "portrait",
  "figure_count": "solo",
  "foreground": "rotund purple humanoid with cat-like ears, one arm raised gesturing, smug expression",
  "foreground_palette": ["purple", "lavender", "dark-grey"],
  "background": "purple and magenta energy swirls",
  "background_palette": ["purple", "magenta", "dark-violet"],
  "setting": "void",
  "architecture": "none",
  "time_of_day": "indeterminate",
  "weather": "none",
  "mood": "action",
  "genre_cues": ["anime", "fantasy"],
  "lighting": "ambient",
  "objects": [],
  "animals_creatures": [],
  "food_drink": [],
  "clothing_style": "formal",
  "iconography": ["energy-aura"],
  "emotion": "smug, scheming, commanding",
  "vision_uncertainty": ["gesture-ambiguous-pointing-vs-open-hand"],
  "tags_hub": ["god", "destroyer", "villain", "manipulation", "authority", "tournament", "universe-6", "scheming", "divine", "cat-like", "cosmic", "commander"],
  "tags_filter": ["solo", "mid-shot", "three-quarter", "portrait", "dbs-card", "suspected-ip", "alien-figure"]
}
