{
  "subject": "An armored black knight on a dark heavily armored mount charges forward with lance raised, red banner streaming, bearing down on a fleeing figure in the foreground",
  "subject_known_ip": false,
  "suspected_ip": "",
  "ip_confidence": "none",
  "ip_verified": false,
  "description": "A knight in full black plate armor rides a massive dark mount — the creature is armored and spiked, its form large and imposing. The knight holds a long lance or spear extended forward with one arm; a large red-and-black banner or cloak billows dramatically behind. The mount is at speed, churning forward into the viewer's space. In the lower foreground, a smaller figure with visible hair is fleeing or falling, small and dwarfed by the charging knight. The sky is stormy and turbulent, clouds lit from below in blue-grey and gold tones. The overall palette is dark armor, red fabric, and a dramatic open sky.",
  "facing": "forward",
  "composition": "wide",
  "mode": "action",
  "figure_count": "duo",
  "foreground": "fleeing or falling small figure with hair visible, lower left",
  "foreground_palette": ["blonde", "grey", "dark"],
  "background": "stormy sky, blue-grey clouds lit from below, distant horizon",
  "background_palette": ["blue-grey", "dark blue", "gold", "storm grey"],
  "setting": "other",
  "architecture": "none",
  "time_of_day": "twilight",
  "weather": "storm",
  "mood": "grim",
  "genre_cues": ["fantasy", "dark-fantasy"],
  "lighting": "rim",
  "objects": ["lance", "banner", "armor", "spear"],
  "animals_creatures": ["armored-mount", "dark-horse"],
  "food_drink": [],
  "clothing_style": "armor",
  "iconography": ["red banner", "black plate armor"],
  "emotion": "aggression, domination, pursuit; the fleeing figure conveys terror",
  "tags_hub": ["knight", "cavalry", "pursuit", "black-armor", "villain", "war", "dark-fantasy", "dominance", "storm", "banner", "horseman", "lance"],
  "tags_filter": ["duo", "wide-shot", "action-mode", "forward-facing", "black-magic", "creature-knight", "hexproof", "first-strike"],
  "vision_uncertainty": []
}
