{
  "subject": "An animated gingerbread man figure decorated with white icing piping, candy buttons, and confectionery details, posed mid-stride as if running",
  "subject_known_ip": false,
  "suspected_ip": "",
  "ip_confidence": "none",
  "ip_verified": false,
  "description": "A gingerbread man figure stands in a confectionery setting, his baked-cookie body trimmed with swirls of white icing along the arms, legs, and head. Round candy buttons mark the torso and a small icing-piped face gives him an alert, slightly mischievous expression. The figure leans forward in a running pose with arms raised. Surrounding him are other baked-good and candy elements — gingerbread shapes, icing, sugary architectural pieces — suggesting a kitchen, oven interior, or candy-house environment. Warm browns dominate the palette, accented by creamy whites and small bright candy colors. The lighting is soft and warm, like firelight or oven-glow.",
  "facing": "three-quarter",
  "composition": "mid-shot",
  "mode": "action",
  "figure_count": "solo",
  "foreground": "gingerbread figure with icing trim and candy buttons in a running pose",
  "foreground_palette": ["warm-brown", "cream-white", "caramel", "red"],
  "background": "confectionery / baked-goods environment with other gingerbread and candy shapes",
  "background_palette": ["dark-brown", "amber", "cream", "shadowed-black"],
  "setting": "indoor",
  "architecture": "organic",
  "time_of_day": "indeterminate",
  "weather": "none",
  "mood": "comedic",
  "genre_cues": ["fantasy", "fairy-tale", "storybook"],
  "lighting": "soft",
  "objects": ["icing", "candy-buttons", "gingerbread", "baked-goods"],
  "animals_creatures": ["gingerbread-golem", "food-golem"],
  "food_drink": ["gingerbread", "icing", "candy", "cookies"],
  "clothing_style": "none",
  "iconography": ["candy", "frosting-swirls"],
  "emotion": "alert, animated, mid-action — wide-eyed cookie-face with a hint of mischief",
  "tags_hub": [
    "gingerbread",
    "food",
    "baking",
    "cookies",
    "candy",
    "kitchen",
    "fairy-tale",
    "storybook",
    "golem",
    "animated-object",
    "running",
    "confection",
    "sweets",
    "comic-relief"
  ],
  "tags_filter": [
    "solo",
    "mid-shot",
    "action-pose",
    "three-quarter-facing",
    "scene-mode",
    "no-face-human",
    "artifact-creature",
    "food-golem",
    "colorless",
    "haste"
  ]
}
