{
  "subject": "A robed vampire cleric standing with arms raised in a ceremonial gesture inside a gothic cathedral",
  "subject_known_ip": false,
  "suspected_ip": "Vito, Thorn of the Dusk Rose",
  "ip_confidence": "high",
  "ip_verified": false,
  "description": "A pale, dark-haired vampire cleric stands at the center of the frame, arms raised wide in a ritualistic or sermonizing gesture. He wears heavy ecclesiastical robes with a high standing collar in deep crimson and black, accented with gold trim. The setting is the interior of a gothic cathedral: tall pointed arches, ribbed vaults, and stained-glass-style window detail recede behind him into a dim, candlelit gloom. Cool blue-grey moonlight filters through the architecture, contrasting with warm reddish glows below. His stance and elevated arms suggest preaching, blessing, or invoking — a vampiric figure cast in the iconography of a priest.",
  "facing": "forward",
  "composition": "mid-shot",
  "mode": "portrait",
  "figure_count": "solo",
  "foreground": "robed vampire cleric with arms raised, dark hair, pale skin, ornate ecclesiastical vestments",
  "foreground_palette": ["crimson", "black", "gold", "pale-flesh", "dark-brown"],
  "background": "gothic cathedral interior with pointed arches, ribbed vaults, and dim moonlit recesses",
  "background_palette": ["slate-blue", "charcoal", "muted-violet", "warm-amber"],
  "setting": "indoor",
  "architecture": "gothic",
  "time_of_day": "night",
  "weather": "calm",
  "mood": "grim",
  "genre_cues": ["fantasy", "gothic-horror", "dark-fantasy"],
  "lighting": "chiaroscuro",
  "objects": ["ecclesiastical-robes", "gold-trim", "high-collar"],
  "animals_creatures": ["vampire"],
  "food_drink": [],
  "clothing_style": "formal",
  "iconography": ["raised-arms", "preaching-pose", "high-collar", "ritual-gesture"],
  "emotion": "rapturous, commanding, devotional — body language of a preacher mid-sermon or a celebrant invoking",
  "tags_hub": [
    "vampire",
    "cleric",
    "priest",
    "ritual",
    "gothic",
    "cathedral",
    "robed-figure",
    "sermon",
    "blessing",
    "night",
    "blood",
    "undead",
    "religion",
    "dark-fantasy"
  ],
  "tags_filter": [
    "solo",
    "mid-shot",
    "forward-facing",
    "portrait-mode",
    "male-figure",
    "creature-vampire",
    "creature-cleric",
    "legendary",
    "black-magic",
    "lifegain",
    "lifeloss"
  ]
}
