{
  "subject": "A horned, winged devil cackling mid-air with arms thrown wide above a crowd of smaller imps amid a rain of fire and embers",
  "subject_known_ip": false,
  "suspected_ip": "",
  "ip_confidence": "none",
  "ip_verified": false,
  "description": "A red-skinned devil with curling black horns, leathery bat-like wings, and a long whipping tail floats above a churning mass of smaller imps. Its arms are flung wide and its head is tipped back in open-mouthed laughter, the silhouette posed almost theatrically against a hellscape of orange flame, drifting embers, and silhouetted clawing hands rising from the lower edge of the frame. The palette is dominated by saturated reds, oranges, and blacks, with bright cinder highlights ringing the figure. Smoke and ash blur the background while the foreground devil is rim-lit by the surrounding inferno, giving the whole image a chaotic, gleeful, hellfire-circus mood.",
  "facing": "forward",
  "composition": "mid-shot",
  "mode": "action",
  "figure_count": "group",
  "foreground": "central horned devil with outstretched arms and wings, laughing mid-flight",
  "foreground_palette": ["red", "black", "orange", "ember-yellow"],
  "background": "burning hellscape with rising flames, embers, smoke, and a swarm of smaller imps with raised clawing arms",
  "background_palette": ["orange", "deep-red", "black", "ash-gray"],
  "setting": "other",
  "architecture": "none",
  "time_of_day": "indeterminate",
  "weather": "fire",
  "mood": "grim",
  "genre_cues": ["fantasy", "dark-fantasy", "horror"],
  "lighting": "rim",
  "objects": ["embers", "ash", "flames"],
  "animals_creatures": ["devil", "imps", "winged-fiend"],
  "food_drink": [],
  "clothing_style": "naked",
  "iconography": ["horns", "bat-wings", "fire", "tail", "claws"],
  "emotion": "manic glee, open-mouthed laughter, theatrical exultation",
  "tags_hub": [
    "devil",
    "demon",
    "imp",
    "fire",
    "hell",
    "wings",
    "horns",
    "laughter",
    "chaos",
    "trickster",
    "swarm",
    "inferno"
  ],
  "tags_filter": [
    "group",
    "mid-shot",
    "forward-facing",
    "scene-mode",
    "no-face-obscured",
    "creature-devil",
    "red-magic",
    "flying",
    "winged-figure",
    "central-figure"
  ]
}
