{
  "subject": "Gastly, a ghostly gas Pokemon depicted as a large purple-black sphere with glowing eyes, surrounded by wispy dark smoke",
  "subject_known_ip": false,
  "suspected_ip": "Gastly",
  "ip_confidence": "high",
  "ip_verified": false,
  "description": "A large round gaseous creature with a near-perfectly circular dark body fills most of the card art. It has two large white eyes with dark pupils and a wide mouth. The body is deepest at its center and fades outward into wispy purple-black gas tendrils that blend into the surrounding darkness. The overall color palette is deep purple and black with faint lighter outlines. The background is dark with a subtle purple glow. The art style is consistent with the Evolutions set's homage to the original Base Set illustrative style. The figure has no limbs and floats freely.",
  "facing": "forward",
  "composition": "close-up",
  "mode": "portrait",
  "figure_count": "solo",
  "foreground": "Large round gaseous dark body with glowing eyes, wispy purple-black smoke tendrils",
  "foreground_palette": ["deep purple", "black", "white"],
  "background": "Dark background with faint purple atmospheric glow",
  "background_palette": ["black", "dark purple", "indigo"],
  "setting": "void",
  "architecture": "none",
  "time_of_day": "night",
  "weather": "fog",
  "mood": "horror",
  "genre_cues": ["anime", "horror", "fantasy"],
  "lighting": "ambient",
  "objects": [],
  "animals_creatures": ["Gastly", "ghost"],
  "food_drink": [],
  "clothing_style": "none",
  "iconography": ["gas-tendrils", "glowing-eyes"],
  "emotion": "menacing neutrality, unsettling stillness",
  "tags_hub": ["ghost", "darkness", "gas", "haunting", "purple", "night", "eerie", "fog", "floating", "void", "horror"],
  "tags_filter": ["solo", "forward-facing", "close-up", "portrait-mode", "no-face"],
  "vision_uncertainty": []
}
