{
  "subject": "A humanoid figure in close-up, a curved blade pressed flat against the forehead, blood trickling from a cut — smiling with calm menace",
  "subject_known_ip": false,
  "suspected_ip": "Toshiro Umezawa",
  "ip_confidence": "med",
  "ip_verified": false,
  "description": "An extreme close-up of a humanoid figure's face, hair loose and dark, a curved blade held horizontally across the forehead with a thin line of blood where it nicks the skin. The figure's expression is composed and almost pleased — a controlled, self-assured smile. The background is a soft purple-lavender out-of-focus glow suggesting an indoor or forest setting at night. The blade is clearly visible but the hand gripping its far end is partially cropped. The image reads as a deliberate self-display of danger rather than a combat scene.",
  "facing": "forward",
  "composition": "close-up",
  "mode": "portrait",
  "figure_count": "solo",
  "foreground": "Humanoid figure with blade pressed to forehead, blood visible",
  "foreground_palette": ["tan", "dark-brown", "red", "silver"],
  "background": "Soft purple-lavender blur, suggestion of vertical shapes",
  "background_palette": ["lavender", "purple", "indigo"],
  "setting": "other",
  "architecture": "none",
  "time_of_day": "indeterminate",
  "weather": "none",
  "mood": "grim",
  "genre_cues": ["fantasy", "samurai"],
  "lighting": "soft",
  "objects": ["curved blade", "blood"],
  "animals_creatures": [],
  "food_drink": [],
  "clothing_style": "medieval",
  "iconography": ["blade-to-forehead"],
  "emotion": "calm menace, self-possession, controlled smile",
  "tags_hub": ["blade", "blood", "samurai", "villain", "self-interest", "danger", "smirk", "warrior", "defiance", "close-call"],
  "tags_filter": ["solo", "close-up", "portrait-mode", "forward-facing", "black-magic", "instant", "creature-spell"]
}
