{
  "subject": "Hatsune Miku, the virtual idol, in a dynamic stage pose with long twin-tails, wearing her signature outfit",
  "subject_known_ip": true,
  "suspected_ip": "Hatsune Miku",
  "ip_confidence": "high",
  "ip_verified": false,
  "description": "A female-presenting figure with extremely long twin-tailed hair in a vivid teal color strikes a dynamic, expressive pose. She wears a dark top and a short skirt with accents, and her arms are extended outward in a performance gesture. The background features bold, stylized large text — a visual design motif — and the overall aesthetic is high-energy and stage-performance-oriented. The composition is tightly framed around the upper body and arms, with a sense of forward motion.",
  "facing": "forward",
  "composition": "mid-shot",
  "mode": "action",
  "figure_count": "solo",
  "foreground": "female-presenting figure with long teal twin-tails in performance pose",
  "foreground_palette": ["teal", "black", "white", "dark-grey"],
  "background": "stylized large bold text overlay, stage-design aesthetic",
  "background_palette": ["dark-blue", "teal", "white"],
  "setting": "other",
  "architecture": "none",
  "time_of_day": "indeterminate",
  "weather": "none",
  "mood": "action",
  "genre_cues": ["anime", "idol", "vocaloid"],
  "lighting": "rim",
  "objects": [],
  "animals_creatures": [],
  "food_drink": [],
  "clothing_style": "futuristic",
  "iconography": ["twin-tails", "stage-performance"],
  "emotion": "energetic, expressive, performing",
  "tags_hub": ["idol", "singer", "performance", "music", "twin-tails", "teal", "dance", "stage", "night", "vocaloid"],
  "tags_filter": ["solo", "mid-shot", "action", "forward-facing", "female-figure"],
  "vision_uncertainty": ["low-resolution-source", "hair-eye-skin-unresolved"]
}
