{
  "subject": "Darkwing Duck's living room chair set — a cozy domestic scene with a large purple armchair, ottoman, side table, steaming mug, and warm lamp light",
  "subject_known_ip": true,
  "suspected_ip": "Darkwing's Chair Set / Darkwing Duck's lair (Darkwing Duck)",
  "ip_confidence": "high",
  "ip_verified": false,
  "description": "A warm, inviting interior scene depicts a large cushioned purple armchair and matching footrest ottoman arranged on a patterned rug. A small round side table beside the chair holds a steaming mug. A floor lamp with a warm amber shade provides soft lighting. On the wall hangs a framed painting. A window with blue curtains shows night outside. The overall atmosphere is deeply cozy and domestic — a private retreat. The only detail suggesting heroic identity is the lived-in specificity of the furnishing arrangement, consistent with a superhero's secret relaxation spot.",
  "facing": "n/a",
  "composition": "wide",
  "mode": "narrative",
  "figure_count": "none",
  "foreground": "Large purple armchair and footrest ottoman on patterned rug",
  "foreground_palette": ["purple", "orange", "brown", "red"],
  "background": "Warm domestic interior, framed painting, blue curtain window at night",
  "background_palette": ["warm-brown", "amber", "blue"],
  "setting": "indoor",
  "architecture": "modern",
  "time_of_day": "night",
  "weather": "none",
  "mood": "cozy",
  "genre_cues": ["animation", "comedy"],
  "lighting": "soft",
  "objects": ["armchair", "ottoman", "side table", "steaming mug", "floor lamp", "framed painting", "curtains"],
  "animals_creatures": [],
  "food_drink": ["hot beverage"],
  "clothing_style": "none",
  "iconography": ["cozy domestic furniture", "armchair"],
  "emotion": "calm domestic comfort, restful sanctuary",
  "tags_hub": ["cozy", "chair", "living-room", "domestic", "sanctuary", "warmth", "night", "armchair", "tea", "rest", "interior", "comfort"],
  "tags_filter": ["no-face", "wide", "narrative", "amber-magic", "item-card"],
  "vision_uncertainty": []
}
