{
  "subject": "Yanmega, a large dragonfly-like Pokemon with a green segmented body, multiple wings, and large compound eyes, shown in flight",
  "subject_known_ip": false,
  "suspected_ip": "Yanmega",
  "ip_confidence": "high",
  "ip_verified": false,
  "description": "A large dragonfly-type creature is depicted in dynamic mid-flight, its green segmented body angled with wings spread wide. Multiple pairs of transparent wings are visible. Large compound eyes dominate the head. The creature has a long abdomen ending in a tail fan. The background is a bright open sky with light cloud haze, giving the composition a sense of speed and aerial dominance. The mood is aggressive and predatory.",
  "facing": "three-quarter",
  "composition": "mid-shot",
  "mode": "action",
  "figure_count": "solo",
  "foreground": "large green dragonfly-like creature in flight with multiple wing pairs and segmented body",
  "foreground_palette": ["green", "dark-green", "teal"],
  "background": "bright sky with diffuse cloud-light haze",
  "background_palette": ["light-blue", "white", "pale-yellow"],
  "setting": "other",
  "architecture": "none",
  "time_of_day": "day",
  "weather": "clear",
  "mood": "action",
  "genre_cues": ["anime", "fantasy"],
  "lighting": "ambient",
  "objects": [],
  "animals_creatures": ["dragonfly", "insect-creature", "giant-insect"],
  "food_drink": [],
  "clothing_style": "none",
  "iconography": [],
  "emotion": "aggressive, focused, predatory posture in flight",
  "tags_hub": ["dragonfly", "insect", "flying", "wings", "predator", "green-creature", "speed", "aerial", "giant-insect", "compound-eyes", "creature-portrait"],
  "tags_filter": ["solo", "mid-shot", "three-quarter", "action-mode", "creature-only", "flying"],
  "vision_uncertainty": []
}
