{
  "subject": "Majin Buu in close-up portrait, pink rotund body, antenna, wide grin",
  "subject_known_ip": false,
  "suspected_ip": "Majin Buu (Dragon Ball Z)",
  "ip_confidence": "high",
  "ip_verified": false,
  "description": "A large pink rotund figure fills the frame in a close-up. The figure has a broad, flat face with a very wide grin revealing teeth, a stubby antenna or head protrusion on top, and small beady eyes. The skin tone is a solid bubblegum pink. He wears a white vest or robe-like garment with purple trim. Pink steam or vapor rises from his body. The background is dark, suggesting a void or dramatic dark setting. The overall mood reads as ominous despite the figure's cartoonish design.",
  "facing": "forward",
  "composition": "close-up",
  "mode": "portrait",
  "figure_count": "solo",
  "foreground": "Large pink rotund figure with wide grin, antenna, white vest with purple trim, pink vapor rising",
  "foreground_palette": ["pink", "white", "purple"],
  "background": "Dark void with pink vapor wisps",
  "background_palette": ["dark", "black", "pink"],
  "setting": "void",
  "architecture": "none",
  "time_of_day": "indeterminate",
  "weather": "none",
  "mood": "horror",
  "genre_cues": ["anime", "fantasy"],
  "lighting": "ambient",
  "objects": [],
  "animals_creatures": [],
  "food_drink": [],
  "clothing_style": "robe",
  "iconography": ["steam", "antenna"],
  "emotion": "gleeful menace, ominous glee",
  "tags_hub": ["monster", "villain", "pink", "chaos", "revived", "darkness", "menace", "grin", "supernatural", "candy-colored-horror", "destruction", "evil"],
  "tags_filter": ["solo", "close-up", "portrait", "forward-facing", "anime"],
  "vision_uncertainty": []
}
