{
  "subject": "Young Macintosh from Disney/Pixar's Brave — a muscular young highlander in tartan kilt flexing one arm with a sword in his other hand",
  "subject_known_ip": true,
  "suspected_ip": "Young Macintosh (Brave)",
  "ip_confidence": "high",
  "ip_verified": false,
  "description": "A young, muscular male figure poses confidently in a red-green tartan kilt, one arm raised in a bicep flex while the other hand holds a sword at his side. He wears blue-and-white wristbands and a brown leather strap across his chest. His expression is smug self-satisfaction. Long dark hair falls around his face. In the background, a second figure in similar highland dress is visible holding an axe, likely another Scottish lord's son. The composition communicates youthful arrogance and physical pride — the 'proud son' subtitle reads clear in his body language.",
  "facing": "three-quarter",
  "composition": "mid-shot",
  "mode": "action",
  "figure_count": "duo",
  "foreground": "Muscular young man in tartan kilt flexing arm with sword at side",
  "foreground_palette": ["red", "green", "brown", "blue"],
  "background": "Atmospheric highland setting, second kilted figure with axe visible",
  "background_palette": ["blue", "grey", "dark-purple"],
  "setting": "mountain",
  "architecture": "none",
  "time_of_day": "twilight",
  "weather": "none",
  "mood": "action",
  "genre_cues": ["fantasy", "animation", "highland"],
  "lighting": "ambient",
  "objects": ["sword", "tartan kilt", "wristbands"],
  "animals_creatures": [],
  "food_drink": [],
  "clothing_style": "medieval",
  "iconography": ["tartan", "highland warrior"],
  "emotion": "smug self-satisfaction, flexing pride",
  "tags_hub": ["warrior", "highland", "pride", "youth", "tartan", "scotland", "flex", "sword", "arrogance", "strength", "ally", "clan"],
  "tags_filter": ["duo", "mid-shot", "action", "three-quarter", "steel-magic", "character-card", "storyborn", "ally"],
  "vision_uncertainty": []
}
