{
  "subject": "Professor Magnolia, an elderly woman in a white lab coat, standing in front of a research building and holding out her hand",
  "subject_known_ip": false,
  "suspected_ip": "Professor Magnolia",
  "ip_confidence": "high",
  "ip_verified": false,
  "description": "An older woman with white-gray hair stands in a warm outdoor setting, dressed in a white lab coat over a collared shirt. Her posture is welcoming — one hand extended forward in an offering or inviting gesture, the other relaxed at her side. Behind her is a large brick building consistent with a Pokemon research facility or university, flanked by trees. The card title reads 'Professor Magnolia' in small text at the top. The art is bright and warm-toned, consistent with the Champion's Path Galar-region aesthetic. The holofoil treatment adds shine.",
  "facing": "forward",
  "composition": "mid-shot",
  "mode": "portrait",
  "figure_count": "solo",
  "foreground": "elderly woman in white lab coat, hand extended forward",
  "foreground_palette": ["white", "light gray", "tan"],
  "background": "brick research building with trees, warm daylight",
  "background_palette": ["brick red", "green", "warm tan"],
  "setting": "urban",
  "architecture": "modern",
  "time_of_day": "day",
  "weather": "clear",
  "mood": "peaceful",
  "genre_cues": ["anime"],
  "lighting": "soft",
  "objects": ["building", "trees"],
  "animals_creatures": [],
  "food_drink": [],
  "clothing_style": "formal",
  "iconography": ["lab coat", "research building"],
  "emotion": "welcoming, generous, calm authority",
  "tags_hub": ["professor", "scientist", "researcher", "elder", "mentor", "academia", "kindness", "knowledge", "galar", "trainer-card"],
  "tags_filter": ["solo", "mid-shot", "portrait", "forward-facing", "female-figure", "supporter-card", "trainer-card", "holofoil"]
}
