{
  "subject": "Venipede, a small red and black segmented insect Pokemon with a wheel-like body form and antennae, resting on rocky ground among grasses",
  "subject_known_ip": false,
  "suspected_ip": "Venipede",
  "ip_confidence": "high",
  "ip_verified": false,
  "description": "A small, compact, segmented insect creature crouches low on sandy rocky earth. Its body is predominantly red with dark markings, and it bears prominent antennae or feelers at the front. The body has a curved, almost coiled shape suggesting it could roll into a wheel form. Green grassy plants grow nearby and the ground is earthy and rocky. The composition is close and low to the ground, emphasizing the creature's small scale. The mood is naturalistic, like a field observation of a venomous bug in its habitat.",
  "facing": "three-quarter",
  "composition": "close-up",
  "mode": "portrait",
  "figure_count": "solo",
  "foreground": "small red and black segmented insect creature with antennae, coiled low on rocky earth",
  "foreground_palette": ["red", "black", "dark-grey"],
  "background": "rocky ground with sandy earth, green grasses and low vegetation",
  "background_palette": ["brown", "sandy-tan", "green", "grey"],
  "setting": "other",
  "architecture": "none",
  "time_of_day": "day",
  "weather": "clear",
  "mood": "other",
  "genre_cues": ["anime", "nature", "creature-feature"],
  "lighting": "ambient",
  "objects": [],
  "animals_creatures": ["insect-creature", "poison-type-pokemon", "segmented-bug"],
  "food_drink": [],
  "clothing_style": "none",
  "iconography": [],
  "emotion": "alert, defensive, coiled",
  "tags_hub": ["insect", "poison", "bug", "nature", "small-creature", "coiled", "venomous", "ground-level", "red", "defensive"],
  "tags_filter": ["solo", "close-up", "portrait", "faces-right", "creature-card"],
  "vision_uncertainty": []
}
