{
  "subject": "Granbull, a large stocky bulldog-like creature with prominent oversized fangs and a spiked collar, posed aggressively on rocky dirt terrain",
  "subject_known_ip": true,
  "suspected_ip": "Granbull",
  "ip_confidence": "high",
  "ip_verified": false,
  "description": "A stocky, pink-lavender bulldog creature dominates the frame in a mid-shot composition. It has enormously oversized lower fangs jutting upward, a wide flat snout, and wears a spiked collar around its neck. The creature crouches forward on rocky earth with its arms spread wide, conveying a charging or defensive posture. The background is a warm earthy brown with hints of rock and soil. The creature's expression reads as alert and aggressive despite the flavor text noting its timid nature — the art leans into the imposing physical silhouette.",
  "facing": "forward",
  "composition": "mid-shot",
  "mode": "action",
  "figure_count": "solo",
  "foreground": "Large pink-lavender bulldog creature on rocky ground, spiked collar visible, oversized fangs prominent",
  "foreground_palette": ["lavender", "pink", "gray", "white"],
  "background": "Warm earthy brown rocky terrain, soft light",
  "background_palette": ["brown", "tan", "warm-gray"],
  "setting": "other",
  "architecture": "none",
  "time_of_day": "day",
  "weather": "calm",
  "mood": "action",
  "genre_cues": ["anime", "fantasy"],
  "lighting": "soft",
  "objects": ["spiked-collar"],
  "animals_creatures": ["bulldog-creature", "fanged-beast"],
  "food_drink": [],
  "clothing_style": "none",
  "iconography": [],
  "emotion": "Aggressive posture, wide stance, teeth bared — imposing physical display despite implied timidity",
  "tags_hub": ["bulldog", "fangs", "beast", "guardian", "intimidation", "pink", "aggression", "gentle-giant", "monster", "earth", "brute", "creature"],
  "tags_filter": ["solo", "mid-shot", "forward-facing", "psychic-energy", "stage-2", "fairy-type", "creature"],
  "vision_uncertainty": []
}
