{
  "subject": "A green-skinned goblin in leather armor leaps mid-air through a collapsing wooden structure, arms and legs splayed wide, teeth bared in a grin",
  "subject_known_ip": false,
  "suspected_ip": "",
  "ip_confidence": "none",
  "ip_verified": false,
  "description": "A stout green-skinned goblin bursts through the frame in a leaping pose, arms and legs fully extended outward. It wears dark leather armor with a red cloth belt and red scarf, and heavy boots. Its mouth is open wide, baring teeth in an expression somewhere between aggression and delight. Shattered wooden planks and debris fly outward around it against a warm amber-dust background, suggesting a wall or structure has just been broken through. The painting style is painterly and kinetic, the body fully airborne.",
  "facing": "forward",
  "composition": "mid-shot",
  "mode": "action",
  "figure_count": "solo",
  "foreground": "goblin mid-leap, scattered wooden debris",
  "foreground_palette": ["green", "dark-brown", "red"],
  "background": "warm amber dust and shattered wooden structure",
  "background_palette": ["amber", "tan", "brown"],
  "setting": "urban",
  "architecture": "ruined",
  "time_of_day": "day",
  "weather": "none",
  "mood": "action",
  "genre_cues": ["fantasy"],
  "lighting": "harsh",
  "objects": ["shattered wooden planks", "leather armor", "boots"],
  "animals_creatures": ["goblin"],
  "food_drink": [],
  "clothing_style": "armor",
  "iconography": ["leap", "destruction", "debris"],
  "emotion": "reckless glee, aggression, frenzy",
  "tags_hub": ["goblin", "chaos", "leap", "frenzy", "destruction", "aggression", "reckless", "brawl", "comedy"],
  "tags_filter": ["solo", "mid-shot", "forward-facing", "red-magic", "creature-goblin", "action-mode"]
}
