{
  "subject": "A massive serpentine wurm creature with a gaping fanged maw, emerging from terrain while small armored undead-looking warriors stand in the foreground",
  "subject_known_ip": false,
  "suspected_ip": "",
  "ip_confidence": "none",
  "ip_verified": false,
  "description": "The art crop shows a towering wurm — a massive, segmented serpentine creature — rearing up with its enormous mouth wide open, revealing rows of jagged teeth. Its body is textured with earth-toned scales and patches of green moss or organic material. Debris and dirt scatter around it as it erupts from the ground. In the foreground, two small figures in blue-purple armor with glowing skull-like helmets stand facing the creature, dwarfed by its scale. The background suggests misty ruins or distant city structures under a pale sky. The mood is dread and scale — the viewer is positioned with the tiny soldiers, looking up at something incomprehensibly large.",
  "facing": "forward",
  "composition": "wide",
  "mode": "narrative",
  "figure_count": "group",
  "foreground": "two small armored figures with glowing purple skulls, standing amid scattered debris",
  "foreground_palette": ["blue-purple", "brown", "gray"],
  "background": "misty ruins and pale sky, distant city silhouettes",
  "background_palette": ["gray", "blue-gray", "pale-blue", "tan"],
  "setting": "other",
  "architecture": "ruined",
  "time_of_day": "day",
  "weather": "fog",
  "mood": "horror",
  "genre_cues": ["fantasy", "horror", "epic"],
  "lighting": "ambient",
  "objects": [],
  "animals_creatures": ["wurm", "serpentine-creature", "armored-warriors"],
  "food_drink": [],
  "clothing_style": "armor",
  "iconography": ["skull-helmet", "scale-creature"],
  "emotion": "looming dread — the creature is vast and indifferent, the soldiers small and outmatched",
  "tags_hub": ["monster", "giant-creature", "serpent", "horror", "scale", "undead", "ruins", "maw", "primordial", "dread"],
  "tags_filter": ["group", "wide-shot", "narrative-mode", "scene-mode", "2-figures-foreground", "creature-wurm"],
  "vision_uncertainty": ["secondary-figures-unresolved"]
}
